MALDIDA/__init__.py
MALDIDA/augmenter.py
MALDIDA/dataset.py
MALDIDA/preprocess.py
MALDIDA/spectrum.py
MALDIDA/data/MARISMA/2018/Eschericia/Coli/00109d1f/0_C5/1/1SLin/acqu
MALDIDA/data/MARISMA/2018/Eschericia/Coli/00109d1f/0_C5/1/1SLin/acqus
MALDIDA/data/MARISMA/2018/Eschericia/Coli/00109d1f/0_C5/1/1SLin/fid
MALDIDA/data/MARISMA/2018/Eschericia/Coli/00109d1f/0_C5/1/1SLin/sptype
MALDIDA/data/MARISMA/2018/Eschericia/Coli/00109d1f/0_C5/1/1SLin/pdata/1/1r
MALDIDA/data/MARISMA/2018/Eschericia/Coli/00109d1f/0_C5/1/1SLin/pdata/1/proc
MALDIDA/data/MARISMA/2018/Eschericia/Coli/00109d1f/0_C5/1/1SLin/pdata/1/procs
MALDIDA/data/MARISMA/2018/Eschericia/Coli/0018d75a/0_C9/1/1SLin/acqu
MALDIDA/data/MARISMA/2018/Eschericia/Coli/0018d75a/0_C9/1/1SLin/acqus
MALDIDA/data/MARISMA/2018/Eschericia/Coli/0018d75a/0_C9/1/1SLin/fid
MALDIDA/data/MARISMA/2018/Eschericia/Coli/0018d75a/0_C9/1/1SLin/sptype
MALDIDA/data/MARISMA/2018/Eschericia/Coli/0018d75a/0_C9/1/1SLin/pdata/1/1r
MALDIDA/data/MARISMA/2018/Eschericia/Coli/0018d75a/0_C9/1/1SLin/pdata/1/proc
MALDIDA/data/MARISMA/2018/Eschericia/Coli/0018d75a/0_C9/1/1SLin/pdata/1/procs
maldida-0.2.1.dist-info/licenses/LICENSE
maldida-0.2.1.dist-info/METADATA
maldida-0.2.1.dist-info/WHEEL
maldida-0.2.1.dist-info/top_level.txt
maldida-0.2.1.dist-info/RECORD
