Metadata-Version: 2.4
Name: maldida
Version: 0.2.1
Summary: Preprocessing and augmentation utilities for MALDI-TOF spectra.
Home-page: https://github.com/aguerrerolopez/MALDIDA
Author: Alejandro Guerrero-Lopez
Author-email: aguerrero@imm.uzh.ch
License: LGPL-3.0-or-later
Classifier: Programming Language :: Python :: 3
Classifier: License :: OSI Approved :: GNU Lesser General Public License v3 or later (LGPLv3+)
Classifier: Operating System :: OS Independent
Requires-Python: >=3.8
License-File: LICENSE
Requires-Dist: numpy>=1.20.0
Requires-Dist: pandas
Requires-Dist: scipy
Requires-Dist: matplotlib
Requires-Dist: tqdm
Requires-Dist: h5py
Requires-Dist: scikit-learn
Dynamic: author
Dynamic: author-email
Dynamic: classifier
Dynamic: description
Dynamic: description-content-type
Dynamic: home-page
Dynamic: license
Dynamic: license-file
Dynamic: requires-dist
Dynamic: requires-python
Dynamic: summary
